kmport/__init__.py
kmport-2.2.40.dist-info/LICENSE
kmport-2.2.40.dist-info/METADATA
kmport-2.2.40.dist-info/WHEEL
kmport-2.2.40.dist-info/top_level.txt
kmport-2.2.40.dist-info/RECORD
