Metadata-Version: 2.1
Name: kmport
Version: 2.2.40
Summary: Extended import function
Home-page: https://github.com/kagepark/Import
Author: Kage Park
License: MIT
Platform: UNKNOWN
Classifier: Programming Language :: Python :: 2
Classifier: Programming Language :: Python :: 3
Classifier: License :: OSI Approved :: MIT License
Classifier: Operating System :: OS Independent
License-File: LICENSE
